perdido/__init__.py
perdido/datasets.py
perdido/geocoder.py
perdido/geoparser.py
perdido/geoparser_tmp.py
perdido/perdido.py
perdido/data/__init__.py
perdido/data/choucas/choucas_perdido.pickle
perdido/data/choucas/choucas_perdido_old.pickle
perdido/data/edda_artfl/__init__.py
perdido/data/edda_artfl/edda_artf_dataset.csv
perdido/data/edda_perdido/0_edda_perdido_dataset_7_nominatim.pickle
perdido/data/edda_perdido/10_edda_perdido_dataset_7_nominatim.pickle
perdido/data/edda_perdido/11_edda_perdido_dataset_7_nominatim.pickle
perdido/data/edda_perdido/12_edda_perdido_dataset_7_nominatim.pickle
perdido/data/edda_perdido/13_edda_perdido_dataset_7_nominatim.pickle
perdido/data/edda_perdido/14_edda_perdido_dataset_7_nominatim.pickle
perdido/data/edda_perdido/15_edda_perdido_dataset_7_nominatim.pickle
perdido/data/edda_perdido/16_edda_perdido_dataset_7_nominatim.pickle
perdido/data/edda_perdido/17_edda_perdido_dataset_7_nominatim.pickle
perdido/data/edda_perdido/18_edda_perdido_dataset_7_nominatim.pickle
perdido/data/edda_perdido/19_edda_perdido_dataset_7_nominatim.pickle
perdido/data/edda_perdido/1_edda_perdido_dataset_7_nominatim.pickle
perdido/data/edda_perdido/20_edda_perdido_dataset_7_nominatim.pickle
perdido/data/edda_perdido/21_edda_perdido_dataset_7_nominatim.pickle
perdido/data/edda_perdido/22_edda_perdido_dataset_7_nominatim.pickle
perdido/data/edda_perdido/23_edda_perdido_dataset_7_nominatim.pickle
perdido/data/edda_perdido/24_edda_perdido_dataset_7_nominatim.pickle
perdido/data/edda_perdido/25_edda_perdido_dataset_7_nominatim.pickle
perdido/data/edda_perdido/26_edda_perdido_dataset_7_nominatim.pickle
perdido/data/edda_perdido/27_edda_perdido_dataset_7_nominatim.pickle
perdido/data/edda_perdido/28_edda_perdido_dataset_7_nominatim.pickle
perdido/data/edda_perdido/29_edda_perdido_dataset_7_nominatim.pickle
perdido/data/edda_perdido/2_edda_perdido_dataset_7_nominatim.pickle
perdido/data/edda_perdido/30_edda_perdido_dataset_7_nominatim.pickle
perdido-0.1.50.dist-info/LICENSE
perdido-0.1.50.dist-info/METADATA
perdido-0.1.50.dist-info/WHEEL
perdido-0.1.50.dist-info/top_level.txt
perdido-0.1.50.dist-info/RECORD
