Metadata-Version: 2.1
Name: perdido
Version: 0.1.50
Summary: PERDIDO Geoparser python library
Home-page: https://github.com/ludovicmoncla/perdido
Author: Ludovic Moncla
Author-email: moncla.ludovic@gmail.com
License: BSD-Clause-2
Keywords: geoparsing named-entity-recognition geographic-information-retrieval toponym-resolution toponym-disambiguation
Classifier: Development Status :: 3 - Alpha
Classifier: License :: OSI Approved :: BSD License
Classifier: Operating System :: POSIX :: Other
Classifier: Operating System :: MacOS
Classifier: Programming Language :: Python :: 3
License-File: LICENSE
Requires-Dist: requests
Requires-Dist: folium
Requires-Dist: lxml
Requires-Dist: geojson
Requires-Dist: gpxpy
Requires-Dist: scikit-learn
Requires-Dist: pandas
Requires-Dist: geopandas
Requires-Dist: matplotlib
Requires-Dist: spacy >=3.3.0
Requires-Dist: display-xml
Requires-Dist: geopy
